manthan/__init__.py
manthan-0.2.dist-info/METADATA
manthan-0.2.dist-info/RECORD
manthan-0.2.dist-info/WHEEL
manthan-0.2.dist-info/top_level.txt
