Metadata-Version: 2.1
Name: manthan
Version: 0.2
Summary: Standard procedures for Manthan
Home-page: https://github.com/hrajiv
Author: Rajiv Hiremagalur
Author-email: rajivhs@manthan.com
License: MIT
Platform: UNKNOWN
